wf_manager/__init__.py
wf_manager/_default_data_manager.py
wf_manager/app.py
wf_manager/example_my_config.py
wf_manager/example_my_workflow.py
wf_manager/fix_inspector_bug.py
wf_manager/inspect_and_modify.py
wf_manager/minimal_module.py
wf_manager/run_workflow.py
wf_manager/workflow_manager.py
wf_manager-0.0.7.dist-info/DESCRIPTION.rst
wf_manager-0.0.7.dist-info/METADATA
wf_manager-0.0.7.dist-info/PKG-INFO-E7450-2D6LM32
wf_manager-0.0.7.dist-info/RECORD
wf_manager-0.0.7.dist-info/SOURCES-E7450-2D6LM32.txt
wf_manager-0.0.7.dist-info/WHEEL
wf_manager-0.0.7.dist-info/entry_points.txt
wf_manager-0.0.7.dist-info/metadata.json
wf_manager-0.0.7.dist-info/top_level.txt
