Metadata-Version: 2.0
Name: wf-manager
Version: 0.0.7
Summary: please describe here wf_manager in one line
Home-page: UNKNOWN
Author: Patrick Kiefer
Author-email: pkiefer@ethz.ch
License: http://opensource.org/licenses/GPL-3.0
Platform: UNKNOWN
